.bowerrc
.coveragerc
AUTHORS.rst
CHANGES.rst
LICENSE.txt
README.rst
requirements.txt
setup.cfg
setup.py
CANberry.egg-info/PKG-INFO
CANberry.egg-info/SOURCES.txt
CANberry.egg-info/dependency_links.txt
CANberry.egg-info/entry_points.txt
CANberry.egg-info/not-zip-safe
CANberry.egg-info/requires.txt
CANberry.egg-info/top_level.txt
canberry/__init__.py
canberry/can_utils.py
canberry/cli.py
canberry/logic.py
canberry/utils.py
canberry/views.py
canberry/bower_components/Flot/.bower.json
canberry/bower_components/Flot/.gitignore
canberry/bower_components/Flot/.travis.yml
canberry/bower_components/Flot/API.md
canberry/bower_components/Flot/CONTRIBUTING.md
canberry/bower_components/Flot/FAQ.md
canberry/bower_components/Flot/LICENSE.txt
canberry/bower_components/Flot/Makefile
canberry/bower_components/Flot/NEWS.md
canberry/bower_components/Flot/PLUGINS.md
canberry/bower_components/Flot/README.md
canberry/bower_components/Flot/component.json
canberry/bower_components/Flot/excanvas.js
canberry/bower_components/Flot/excanvas.min.js
canberry/bower_components/Flot/flot.jquery.json
canberry/bower_components/Flot/jquery.colorhelpers.js
canberry/bower_components/Flot/jquery.flot.canvas.js
canberry/bower_components/Flot/jquery.flot.categories.js
canberry/bower_components/Flot/jquery.flot.crosshair.js
canberry/bower_components/Flot/jquery.flot.errorbars.js
canberry/bower_components/Flot/jquery.flot.fillbetween.js
canberry/bower_components/Flot/jquery.flot.image.js
canberry/bower_components/Flot/jquery.flot.js
canberry/bower_components/Flot/jquery.flot.navigate.js
canberry/bower_components/Flot/jquery.flot.pie.js
canberry/bower_components/Flot/jquery.flot.resize.js
canberry/bower_components/Flot/jquery.flot.selection.js
canberry/bower_components/Flot/jquery.flot.stack.js
canberry/bower_components/Flot/jquery.flot.symbol.js
canberry/bower_components/Flot/jquery.flot.threshold.js
canberry/bower_components/Flot/jquery.flot.time.js
canberry/bower_components/Flot/jquery.js
canberry/bower_components/Flot/package.json
canberry/bower_components/Flot/examples/background.png
canberry/bower_components/Flot/examples/examples.css
canberry/bower_components/Flot/examples/index.html
