Metadata-Version: 1.0
Name: CANberry
Version: 0.3
Summary: A small web app for Raspberry Pi with a controller area network (CAN) bus.
Home-page: http://canberry.readthedocs.org/
Author: Andreas Wilhelm, Florian Wilhelm
Author-email: Andreas_Wilhelm@gmx.de, Florian.Wilhelm@gmail.com
License: new-BSD
Platform: UNKNOWN
